epsagon/__init__.py
epsagon/cacert.pem
epsagon/common.py
epsagon/constants.py
epsagon/event.py
epsagon/handler.py
epsagon/http_filters.py
epsagon/patcher.py
epsagon/trace.py
epsagon/trace_encoder.py
epsagon/trace_transports.py
epsagon/utils.py
epsagon/events/__init__.py
epsagon/events/azure.py
epsagon/events/botocore.py
epsagon/events/celery.py
epsagon/events/dbapi.py
epsagon/events/greengrasssdk.py
epsagon/events/httplib2.py
epsagon/events/kafka.py
epsagon/events/pymongo.py
epsagon/events/pynamodb.py
epsagon/events/pyqldb.py
epsagon/events/qcloud_cos.py
epsagon/events/redis.py
epsagon/events/requests.py
epsagon/events/sqlalchemy.py
epsagon/events/tornado_client.py
epsagon/events/urllib.py
epsagon/events/urllib3.py
epsagon/modules/MySQLdb.py
epsagon/modules/__init__.py
epsagon/modules/azure.py
epsagon/modules/botocore.py
epsagon/modules/celery.py
epsagon/modules/db_wrapper.py
epsagon/modules/django.py
epsagon/modules/fastapi.py
epsagon/modules/flask.py
epsagon/modules/general_wrapper.py
epsagon/modules/greengrasssdk.py
epsagon/modules/gunicorn.py
epsagon/modules/httplib2.py
epsagon/modules/kafka.py
epsagon/modules/logging.py
epsagon/modules/pg8000.py
epsagon/modules/psycopg2.py
epsagon/modules/pymongo.py
epsagon/modules/pymysql.py
epsagon/modules/pynamodb.py
epsagon/modules/pyqldb.py
epsagon/modules/qcloud_cos.py
epsagon/modules/redis.py
epsagon/modules/requests.py
epsagon/modules/sqlalchemy.py
epsagon/modules/tornado.py
epsagon/modules/urllib.py
epsagon/modules/urllib3.py
epsagon/runners/__init__.py
epsagon/runners/aws_lambda.py
epsagon/runners/azure_function.py
epsagon/runners/celery.py
epsagon/runners/django.py
epsagon/runners/fastapi.py
epsagon/runners/flask.py
epsagon/runners/gcp_function.py
epsagon/runners/python_function.py
epsagon/runners/tencent_function.py
epsagon/runners/tornado.py
epsagon/triggers/__init__.py
epsagon/triggers/aws_lambda.py
epsagon/triggers/azure_function.py
epsagon/triggers/http.py
epsagon/triggers/tencent_function.py
epsagon-1.82.0.dist-info/LICENSE
epsagon-1.82.0.dist-info/METADATA
epsagon-1.82.0.dist-info/WHEEL
epsagon-1.82.0.dist-info/entry_points.txt
epsagon-1.82.0.dist-info/top_level.txt
epsagon-1.82.0.dist-info/RECORD
