Metadata-Version: 2.1
Name: epsagon
Version: 1.82.0
Summary: Epsagon Instrumentation for Python
Home-page: https://github.com/epsagon/epsagon-python
Author: Epsagon
Author-email: support@epsagon.com
License: MIT
Keywords: serverless,microservices,epsagon,tracing,distributed-tracing,lambda,aws-lambda,debugging,monitoring
Classifier: Intended Audience :: Developers
Classifier: Operating System :: OS Independent
Classifier: Programming Language :: Python
Classifier: Programming Language :: Python :: 2
Classifier: Programming Language :: Python :: 2.7
Classifier: Programming Language :: Python :: 3
Classifier: Programming Language :: Python :: 3.6
Classifier: Programming Language :: Python :: 3.7
Classifier: Programming Language :: Python :: 3.8
Classifier: Topic :: Software Development :: Libraries
Classifier: Topic :: Software Development :: Libraries :: Python Modules
License-File: LICENSE
